rust_dtw-0.1.14.dist-info/METADATA
rust_dtw-0.1.14.dist-info/WHEEL
rust_dtw.pyd
rust_dtw-0.1.14.dist-info/RECORD
