Metadata-Version: 2.1
Name: rust-dtw
Version: 0.1.14
Summary: A rust implementation of dynamic time warping with python bindings!
Keywords: dtw timeseries neuroimaging
Home-Page: https://github.com/FL33TW00D/rustDTW
Author: Christopher Fleetwood
License: MIT
